remotivelabs/broker/__about__.py
remotivelabs/broker/__init__.py
remotivelabs/broker/_docs/snippets/client.py
remotivelabs/broker/_docs/snippets/client_list_frames.py
remotivelabs/broker/_docs/snippets/client_subscribe.py
remotivelabs/broker/_docs/snippets/client_subscribe_filtered_frames.py
remotivelabs/broker/_docs/snippets/client_subscribe_filters.py
remotivelabs/broker/_docs/snippets/filters.py
remotivelabs/broker/_docs/snippets/recording_session.py
remotivelabs/broker/_docs/snippets/restbus.py
remotivelabs/broker/_docs/snippets/secoc.py
remotivelabs/broker/_generated/__init__.py
remotivelabs/broker/_generated/common_pb2.py
remotivelabs/broker/_generated/common_pb2.pyi
remotivelabs/broker/_generated/common_pb2_grpc.py
remotivelabs/broker/_generated/diagnostics_api_pb2.py
remotivelabs/broker/_generated/diagnostics_api_pb2.pyi
remotivelabs/broker/_generated/diagnostics_api_pb2_grpc.py
remotivelabs/broker/_generated/google/api/__init__.py
remotivelabs/broker/_generated/google/api/annotations_pb2.py
remotivelabs/broker/_generated/google/api/annotations_pb2.pyi
remotivelabs/broker/_generated/google/api/annotations_pb2_grpc.py
remotivelabs/broker/_generated/google/api/http_pb2.py
remotivelabs/broker/_generated/google/api/http_pb2.pyi
remotivelabs/broker/_generated/google/api/http_pb2_grpc.py
remotivelabs/broker/_generated/network_api_pb2.py
remotivelabs/broker/_generated/network_api_pb2.pyi
remotivelabs/broker/_generated/network_api_pb2_grpc.py
remotivelabs/broker/_generated/recordingsession_api_pb2.py
remotivelabs/broker/_generated/recordingsession_api_pb2.pyi
remotivelabs/broker/_generated/recordingsession_api_pb2_grpc.py
remotivelabs/broker/_generated/restbus_api_pb2.py
remotivelabs/broker/_generated/restbus_api_pb2.pyi
remotivelabs/broker/_generated/restbus_api_pb2_grpc.py
remotivelabs/broker/_generated/system_api_pb2.py
remotivelabs/broker/_generated/system_api_pb2.pyi
remotivelabs/broker/_generated/system_api_pb2_grpc.py
remotivelabs_broker-0.12.0.dist-info/WHEEL
remotivelabs_broker-0.12.0.dist-info/METADATA
remotivelabs_broker-0.12.0.dist-info/RECORD
